pyssdeep/__init__.py
pyssdeep/ssdeep_pep_452.py
pyssdeep/ssdeep_wrapper.py
pyssdeep/bin/linux/fuzzy.so
pyssdeep/bin/linux/fuzzy_64.so
pyssdeep/bin/windows/fuzzy.dll
pyssdeep/bin/windows/fuzzy_64.dll
pyssdeep-1.0.0.data/data/test_file/test_file.txt
tests/__init__.py
tests/test_ssdeep_pep_452.py
tests/test_ssdeep_wrapper.py
tests/__pycache__/__init__.cpython-38.pyc
tests/__pycache__/test_ssdeep_pep_452.cpython-38-pytest-6.1.1.pyc
tests/__pycache__/test_ssdeep_wrapper.cpython-38-pytest-6.1.1.pyc
pyssdeep-1.0.0.dist-info/LICENSE
pyssdeep-1.0.0.dist-info/METADATA
pyssdeep-1.0.0.dist-info/WHEEL
pyssdeep-1.0.0.dist-info/top_level.txt
pyssdeep-1.0.0.dist-info/RECORD
