Metadata-Version: 2.1
Name: pyssdeep
Version: 1.0.0
Summary: The python-wrapper for ssdeep
Home-page: https://github.com/drobotun/pyssdeep/
Author: Evgeny Drobotun
Author-email: drobotun@xakep.ru
License: MIT
Project-URL: Documentation, https://pyssdeep.readthedocs.io/
Project-URL: Source, https://github.com/drobotun/pyssdeep/
Keywords: ssdeep,fuzzy hash,python
Platform: UNKNOWN
Classifier: Development Status :: 4 - Beta
Classifier: Intended Audience :: Developers
Classifier: License :: OSI Approved :: MIT License
Classifier: Programming Language :: Python :: 3.0
Classifier: Programming Language :: Python :: 3.8
